datasette_haversine_point_path/__init__.py
datasette_haversine_point_path-0.1.dist-info/LICENSE
datasette_haversine_point_path-0.1.dist-info/METADATA
datasette_haversine_point_path-0.1.dist-info/WHEEL
datasette_haversine_point_path-0.1.dist-info/entry_points.txt
datasette_haversine_point_path-0.1.dist-info/top_level.txt
datasette_haversine_point_path-0.1.dist-info/RECORD
