Metadata-Version: 2.1
Name: datasette-haversine-point-path
Version: 0.1
Summary: Datasette plugin that adds a custom SQL function for shortest haversine distances between a point and a path
Author: Hamilton Carter
License: Apache License, Version 2.0
Project-URL: Homepage, https://github.com/hcarter333/datasette-haversine-point-path
Project-URL: Changelog, https://github.com/hcarter333/datasette-haversine-point-path/releases
Project-URL: Issues, https://github.com/hcarter333/datasette-haversine-point-path/issues
Project-URL: CI, https://github.com/hcarter333/datasette-haversine-point-path/actions
Classifier: Framework :: Datasette
Classifier: License :: OSI Approved :: Apache Software License
Requires-Python: >=3.8
License-File: LICENSE
Requires-Dist: datasette
Requires-Dist: haversine
Provides-Extra: test
Requires-Dist: pytest ; extra == 'test'
